svk_validate/__init__.py
svk_validate/__main__.py
svk_validate/cli.py
svk_validate/validate.py
svk_validate/schemata/erms-3-0-0/ERMS_v3.xsd
svk_validate/schemata/erms-3-0-0/erms_v3.sch
svk_validate/schemata/erms-3-0-0/erms_v3_sch_compiled.xsl
svk_validate/schemata/erms-svk-1-0/ERMS-SVK-ARENDE.sch
svk_validate/schemata/erms-svk-1-0/ERMS-SVK-ARENDE.xsd
svk_validate/schemata/erms-svk-1-0/ERMS-SVK-element.xsd
svk_validate/schemata/erms-svk-1-0/erms_svk_1_0_sch_compiled.xsl
svk_validate/schxslt-1.10/LICENSE
svk_validate/schxslt-1.10/README.md
svk_validate/schxslt-1.10/1.0/compile-for-svrl.xsl
svk_validate/schxslt-1.10/1.0/expand.xsl
svk_validate/schxslt-1.10/1.0/include.xsl
svk_validate/schxslt-1.10/1.0/version.xsl
svk_validate/schxslt-1.10/1.0/compile/api-1.0.xsl
svk_validate/schxslt-1.10/1.0/compile/compile-1.0.xsl
svk_validate/schxslt-1.10/2.0/compile-for-svrl.xsl
svk_validate/schxslt-1.10/2.0/expand.xsl
svk_validate/schxslt-1.10/2.0/include.xsl
svk_validate/schxslt-1.10/2.0/pipeline-for-svrl.xsl
svk_validate/schxslt-1.10/2.0/pipeline.xsl
svk_validate/schxslt-1.10/2.0/svrl.xsl
svk_validate/schxslt-1.10/2.0/version.xsl
svk_validate/schxslt-1.10/2.0/compile/api-2.0.xsl
svk_validate/schxslt-1.10/2.0/compile/compile-2.0.xsl
svk_validate/schxslt-1.10/2.0/compile/functions.xsl
svk_validate/schxslt-1.10/2.0/compile/templates.xsl
svk_validate/schxslt-1.10/2.0/util/normalize-svrl.xsl
svk_validate-0.3.dist-info/LICENSE
svk_validate-0.3.dist-info/METADATA
svk_validate-0.3.dist-info/WHEEL
svk_validate-0.3.dist-info/entry_points.txt
svk_validate-0.3.dist-info/top_level.txt
svk_validate-0.3.dist-info/RECORD
