Metadata-Version: 2.1
Name: svk-validate
Version: 0.3
Summary: A simple tool for validating XML-files against Church of Sweden's adaptation of ERMS.
Author: Svenska kyrkans arkiv i Uppsala
License: Apache-2.0
Project-URL: Homepage, https://github.com/svkau/svk-validate
Project-URL: Changelog, https://github.com/svkau/svk-validate/releases
Project-URL: Issues, https://github.com/svkau/svk-validate/issues
Project-URL: CI, https://github.com/svkau/svk-validate/actions
Classifier: License :: OSI Approved :: Apache Software License
Requires-Python: >=3.8
License-File: LICENSE
Requires-Dist: click
Requires-Dist: saxonche
Requires-Dist: lxml
Provides-Extra: test
Requires-Dist: pytest ; extra == 'test'
